210050135/lab2 /q2/fulladder.vhd
library IEEE;
use IEEE.STD_LOGIC_1164.ALL;

entity FullAdder is
    Port ( A : in  STD_LOGIC;
           B : in  STD_LOGIC;
           Cin : in  STD_LOGIC;
           Sum : out  STD_LOGIC;
           Cout : out  STD_LOGIC);
end FullAdder;

architecture Behavioral of FullAdder is
begin
  Sum <= A xor B xor Cin;
  Cout <= (A and B) or (Cin and (A xor B));
end Behavioral;

lab2/210050135/Q2/RCA8.vhd
library IEEE;
use IEEE.std_logic_1164.all;

entity RCA8 is
    port(a, b: in std_logic_vector(7 downto 0);
    sum: out std_logic_vector(7 downto 0);
    cout: out std_logic);
end entity;

architecture Structural of RCA8 is

    component FullAdder is
      Port ( a, b : in  STD_LOGIC;
             cin : in  STD_LOGIC;
             sum : out  STD_LOGIC;
             cout : out  STD_LOGIC);
    end component;
    
    signal c : STD_LOGIC_VECTOR(7 downto 0);
    
    begin
    
    U0: FullAdder 
    port map(a(0), b(0), '0', sum(0), c(1));
    U1: FullAdder 
    port map(a(1), b(1), c(1), sum(1), c(2));
    U2: FullAdder 
    port map(a(2), b(2), c(2), sum(2), c(3));
    U3: FullAdder 
    port map(a(3), b(3), c(3), sum(3), c(4));
    U4: FullAdder 
    port map(a(4), b(4), c(4), sum(4), c(5));
    U5: FullAdder 
    port map(a(5), b(5), c(5), sum(5), c(6));
    U6: FullAdder 
    port map(a(6), b(6), c(6), sum(6), c(7));
    U7: FullAdder 
    port map(a(7), b(7), c(7), sum(7), cout);
    
    end Structural;

lab2/210050135/Q2/tb.vhd
library IEEE;
use IEEE.std_logic_1164.all;

entity tb is
end entity;

architecture tb of tb is
    signal x1, x2, sum_out: std_logic_vector(7 downto 0);
    signal power: std_logic;
    -- signal g: std_logic;
    component RCA8 is
        port(a, b: in std_logic_vector(7 downto 0);
        sum: out std_logic_vector(7 downto 0);
        cout: out std_logic);
    end component;
begin    
    dut_instances: RCA8
    port map( a => x1,b => x2, sum => sum_out,cout => power );    
    process
    begin
        x1  <= "10100100";
        x2  <= "11101011";
        wait for 1 ns;
        x1  <= "11111111";
        x2  <= "10101011";
        wait for 1 ns;
       
    end process;
end architecture;

210050135/lab2 /q2/RCA8.vcd
$date
  Fri Feb  3 14:45:24 2023
$end
$version
  GHDL v0
$end
$timescale
  1 fs
$end
$scope module standard $end
$upscope $end
$scope module textio $end
$upscope $end
$scope module std_logic_1164 $end
$upscope $end
$scope module tb $end
$var reg 8 ! x1[7:0] $end
$var reg 8 " x2[7:0] $end
$var reg 8 # sum_out[7:0] $end
$var reg 1 $ power $end
$scope module dut_instances $end
$var reg 8 % a[7:0] $end
$var reg 8 & b[7:0] $end
$var reg 8 ' sum[7:0] $end
$var reg 1 ( cout $end
$var reg 8 ) c[7:0] $end
$scope module u0 $end
$var reg 1 * a $end
$var reg 1 + b $end
$var reg 1 , cin $end
$var reg 1 - sum $end
$var reg 1 . cout $end
$upscope $end
$scope module u1 $end
$var reg 1 / a $end
$var reg 1 0 b $end
$var reg 1 1 cin $end
$var reg 1 2 sum $end
$var reg 1 3 cout $end
$upscope $end
$scope module u2 $end
$var reg 1 4 a $end
$var reg 1 5 b $end
$var reg 1 6 cin $end
$var reg 1 7 sum $end
$var reg 1 8 cout $end
$upscope $end
$scope module u3 $end
$var reg 1 9 a $end
$var reg 1 : b $end
$var reg 1 ; cin $end
$var reg 1 < sum $end
$var reg 1 = cout $end
$upscope $end
$scope module u4 $end
$var reg 1 > a $end
$var reg 1 ? b $end
$var reg 1 @ cin $end
$var reg 1 A sum $end
$var reg 1 B cout $end
$upscope $end
$scope module u5 $end
$var reg 1 C a $end
$var reg 1 D b $end
$var reg 1 E cin $end
$var reg 1 F sum $end
$var reg 1 G cout $end
$upscope $end
$scope module u6 $end
$var reg 1 H a $end
$var reg 1 I b $end
$var reg 1 J cin $end
$var reg 1 K sum $end
$var reg 1 L cout $end
$upscope $end
$scope module u7 $end
$var reg 1 M a $end
$var reg 1 N b $end
$var reg 1 O cin $end
$var reg 1 P sum $end
$var reg 1 Q cout $end
$upscope $end
$upscope $end
$upscope $end
$enddefinitions $end
#0
b10100100 !
b11101011 "
b10001111 #
1$
b10100100 %
b11101011 &
b10001111 '
1(
b1100000U )
0*
1+
0,
1-
0.
0/
10
01
12
03
14
05
06
17
08
09
1:
0;
1<
0=
0>
0?
0@
0A
0B
1C
1D
0E
0F
1G
0H
1I
1J
0K
1L
1M
1N
1O
1P
1Q
#1000000
b11111111 !
b10101011 "
b10101010 #
b11111111 %
b10101011 &
b10101010 '
b1111111U )
1*
0-
1.
1/
11
12
13
16
07
18
19
1;
1<
1=
1>
1@
0A
1B
1E
1F
1H
0I
#2000000
b10100100 !
b11101011 "
b10001111 #
b10100100 %
b11101011 &
b10001111 '
b1100000U )
0*
1-
0.
0/
01
12
03
06
17
08
09
0;
1<
0=
0>
0@
0A
0B
0E
0F
0H
1I
#3000000
b11111111 !
b10101011 "
b10101010 #
b11111111 %
b10101011 &
b10101010 '
b1111111U )
1*
0-
1.
1/
11
12
13
16
07
18
19
1;
1<
1=
1>
1@
0A
1B
1E
1F
1H
0I
#4000000
b10100100 !
b11101011 "
b10001111 #
b10100100 %
b11101011 &
b10001111 '
b1100000U )
0*
1-
0.
0/
01
12
03
06
17
08
09
0;
1<
0=
0>
0@
0A
0B
0E
0F
0H
1I
#5000000
b11111111 !
b10101011 "
b10101010 #
b11111111 %
b10101011 &
b10101010 '
b1111111U )
1*
0-
1.
1/
11
12
13
16
07
18
19
1;
1<
1=
1>
1@
0A
1B
1E
1F
1H
0I
#6000000
b10100100 !
b11101011 "
b10001111 #
b10100100 %
b11101011 &
b10001111 '
b1100000U )
0*
1-
0.
0/
01
12
03
06
17
08
09
0;
1<
0=
0>
0@
0A
0B
0E
0F
0H
1I
#7000000
b11111111 !
b10101011 "
b10101010 #
b11111111 %
b10101011 &
b10101010 '
b1111111U )
1*
0-
1.
1/
11
12
13
16
07
18
19
1;
1<
1=
1>
1@
0A
1B
1E
1F
1H
0I
#8000000
b10100100 !
b11101011 "
b10001111 #
b10100100 %
b11101011 &
b10001111 '
b1100000U )
0*
1-
0.
0/
01
12
03
06
17
08
09
0;
1<
0=
0>
0@
0A
0B
0E
0F
0H
1I
#9000000
b11111111 !
b10101011 "
b10101010 #
b11111111 %
b10101011 &
b10101010 '
b1111111U )
1*
0-
1.
1/
11
12
13
16
07
18
19
1;
1<
1=
1>
1@
0A
1B
1E
1F
1H
0I
#10000000
b10100100 !
b11101011 "
b10001111 #
b10100100 %
b11101011 &
b10001111 '
b1100000U )
0*
1-
0.
0/
01
12
03
06
17
08
09
0;
1<
0=
0>
0@
0A
0B
0E
0F
0H
1I
#11000000
b11111111 !
b10101011 "
b10101010 #
b11111111 %
b10101011 &
b10101010 '
b1111111U )
1*
0-
1.
1/
11
12
13
16
07
18
19
1;
1<
1=
1>
1@
0A
1B
1E
1F
1H
0I
#12000000
b10100100 !
b11101011 "
b10001111 #
b10100100 %
b11101011 &
b10001111 '
b1100000U )
0*
1-
0.
0/
01
12
03
06
17
08
09
0;
1<
0=
0>
0@
0A
0B
0E
0F
0H
1I
#13000000
b11111111 !
b10101011 "
b10101010 #
b11111111 %
b10101011 &
b10101010 '
b1111111U )
1*
0-
1.
1/
11
12
13
16
07
18
19
1;
1<
1=
1>
1@
0A
1B
1E
1F
1H
0I
#14000000
b10100100 !
b11101011 "
b10001111 #
b10100100 %
b11101011 &
b10001111 '
b1100000U )
0*
1-
0.
0/
01
12
03
06
17
08
09
0;
1<
0=
0>
0@
0A
0B
0E
0F
0H
1I
#15000000
b11111111 !
b10101011 "
b10101010 #
b11111111 %
b10101011 &
b10101010 '
b1111111U )
1*
0-
1.
1/
11
12
13
16
07
18
19
1;
1<
1=
1>
1@
0A
1B
1E
1F
1H
0I
#16000000
b10100100 !
b11101011 "
b10001111 #
b10100100 %
b11101011 &
b10001111 '
b1100000U )
0*
1-
0.
0/
01
12
03
06
17
08
09
0;
1<
0=
0>
0@
0A
0B
0E
0F
0H
1I
#17000000
b11111111 !
b10101011 "
b10101010 #
b11111111 %
b10101011 &
b10101010 '
b1111111U )
1*
0-
1.
1/
11
12
13
16
07
18
19
1;
1<
1=
1>
1@
0A
1B
1E
1F
1H
0I
#18000000
b10100100 !
b11101011 "
b10001111 #
b10100100 %
b11101011 &
b10001111 '
b1100000U )
0*
1-
0.
0/
01
12
03
06
17
08
09
0;
1<
0=
0>
0@
0A
0B
0E
0F
0H
1I
#19000000
b11111111 !
b10101011 "
b10101010 #
b11111111 %
b10101011 &
b10101010 '
b1111111U )
1*
0-
1.
1/
11
12
13
16
07
18
19
1;
1<
1=
1>
1@
0A
1B
1E
1F
1H
0I
#20000000
b10100100 !
b11101011 "
b10001111 #
b10100100 %
b11101011 &
b10001111 '
b1100000U )
0*
1-
0.
0/
01
12
03
06
17
08
09
0;
1<
0=
0>
0@
0A
0B
0E
0F
0H
1I
